chkapi/__init__.py
chkapi/api_reader.py
chkapi/app.py
chkapi/events.py
chkapi/exceptions.py
chkapi/search.py
chkapi/storages.py
chkapi/views.py
chkapi/widgets.py
chkapi-0.2.0.dist-info/entry_points.txt
chkapi-0.2.0.dist-info/LICENSE
chkapi-0.2.0.dist-info/WHEEL
chkapi-0.2.0.dist-info/METADATA
chkapi-0.2.0.dist-info/RECORD
